.DS_Store
tests/__init__.py
utime/.DS_Store
utime/__init__.py
utime/_defaults.py
utime/version.py
utime/augmentation/__init__.py
utime/augmentation/augmenters.py
utime/augmentation/elastic_deformation.py
utime/bin/.DS_Store
utime/bin/__init__.py
utime/bin/batch_speed.py
utime/bin/channels.py
utime/bin/cm.py
utime/bin/cv_experiment.py
utime/bin/cv_split.py
utime/bin/evaluate.py
utime/bin/extract.py
utime/bin/extract_hypno.py
utime/bin/fetch.py
utime/bin/group.py
utime/bin/gui.py
utime/bin/init.py
utime/bin/majority_vote.py
utime/bin/pca.py
utime/bin/predict.py
utime/bin/predict_one.py
utime/bin/preprocess.py
utime/bin/selfsup.py
utime/bin/summary.py
utime/bin/testing.py
utime/bin/train.py
utime/bin/update_views.py
utime/bin/ut.py
utime/bin/defaults/.DS_Store
utime/bin/defaults/deepsleepnet/.DS_Store
utime/bin/defaults/deepsleepnet/finetune.yaml
utime/bin/defaults/deepsleepnet/pretrain.yaml
utime/bin/defaults/deepsleepnet/dataset_configurations/dataset_1.yaml
utime/bin/defaults/usleep/.DS_Store
utime/bin/defaults/usleep/hparams.yaml
utime/bin/defaults/usleep/dataset_configurations/abc.yaml
utime/bin/defaults/usleep/dataset_configurations/ccshs.yaml
utime/bin/defaults/usleep/dataset_configurations/cfs.yaml
utime/bin/defaults/usleep/dataset_configurations/chat.yaml
utime/bin/defaults/usleep/dataset_configurations/dcsm.yaml
utime/bin/defaults/usleep/dataset_configurations/dod_h.yaml
utime/bin/defaults/usleep/dataset_configurations/dod_o.yaml
utime/bin/defaults/usleep/dataset_configurations/hpap.yaml
utime/bin/defaults/usleep/dataset_configurations/isruc_sg1.yaml
utime/bin/defaults/usleep/dataset_configurations/isruc_sg2.yaml
utime/bin/defaults/usleep/dataset_configurations/isruc_sg3.yaml
utime/bin/defaults/usleep/dataset_configurations/mass_c1.yaml
utime/bin/defaults/usleep/dataset_configurations/mass_c3.yaml
utime/bin/defaults/usleep/dataset_configurations/mesa.yaml
utime/bin/defaults/usleep/dataset_configurations/mros.yaml
utime-1.1.7.dist-info/LICENSE.txt
utime-1.1.7.dist-info/METADATA
utime-1.1.7.dist-info/WHEEL
utime-1.1.7.dist-info/entry_points.txt
utime-1.1.7.dist-info/top_level.txt
utime-1.1.7.dist-info/RECORD
