Metadata-Version: 2.1
Name: utime
Version: 1.1.7
Summary: A deep learning framework for automatic PSG sleep analysis.
Home-page: https://github.com/perslev/U-Time
Author: Mathias Perslev
Author-email: map@di.ku.dk
License: LICENSE.txt
Platform: UNKNOWN
Classifier: Environment :: Console
Classifier: Operating System :: POSIX
Classifier: Programming Language :: Python :: 3.6
Classifier: Programming Language :: Python :: 3.7
Classifier: License :: OSI Approved :: MIT License
License-File: LICENSE.txt
Requires-Dist: numpy (>=1.21.5)
Requires-Dist: h5py (>=3.6.0)
Requires-Dist: matplotlib (>=3.4.3)
Requires-Dist: pandas (>=1.3.5)
Requires-Dist: psutil (>=5.9.0)
Requires-Dist: scipy (>=1.7.3)
Requires-Dist: mne (>=0.24.1)
Requires-Dist: tables (>=3.7.0)
Requires-Dist: tabulate (>=0.8.9)
Requires-Dist: wfdb (>=3.4.1)
Requires-Dist: ruamel.yaml (>=0.17.21)
Requires-Dist: scikit-learn (>=1.0.2)
Requires-Dist: requests (>=2.27.1)
Requires-Dist: carbontracker (>=1.1.6)
Requires-Dist: psg-utils (>=0.1.6)
Requires-Dist: tensorflow (>=2.8.0)
Requires-Dist: tensorflow-addons (>=0.16.1)
Requires-Dist: yamlhparams (>=0.2.0)
